{
    "version": "https://jsonfeed.org/version/1",
    "title": "LightWeight JavaScript repositories",
    "home_page_url": "https://azu.github.io/github-search-rss/lightweight-javascript-repo.json",
    "feed_url": "https://azu.github.io/github-search-rss/lightweight-javascript-repo.json",
    "description": "LightWeight JavaScript repositories on GitHub",
    "items": [
        {
            "content_html": "<img src=\"https://avatars.githubusercontent.com/u/35752455?u=456fe6cdbeaa48e0481835d9624440f6375a0e7c&v=4\" width=\"64\" height=\"64\" alt=\"\"/><br/><div>No-Code Tool - Add award-winning text animations with simple HTML data attributes. Lightweight wrapper around GSAP to make complex animations a breeze!</div>",
            "url": "https://github.com/learyjk/animate-text",
            "title": "learyjk/animate-text: No-Code Tool - Add award-winning text animations with simple HTML data attributes. Lightweight wrapper around GSAP to make complex animations a breeze!",
            "date_modified": "2022-10-15T22:01:59.000Z",
            "date_published": "2022-09-23T01:43:38.000Z",
            "author": {
                "name": "learyjk",
                "url": "https://github.com/learyjk"
            }
        },
        {
            "content_html": "<img src=\"https://avatars.githubusercontent.com/u/41121717?u=c423b1bc6f35ae7127e3b66a62b20cde59393205&v=4\" width=\"64\" height=\"64\" alt=\"\"/><br/><div>Lightweight package with functions and hooks for masking data inputs and outputs for Node.JS projects</div>",
            "url": "https://github.com/guilhermeasn/mask-hooks",
            "title": "guilhermeasn/mask-hooks: Lightweight package with functions and hooks for masking data inputs and outputs for Node.JS projects",
            "date_modified": "2022-10-03T22:42:33.000Z",
            "date_published": "2021-03-16T20:59:34.000Z",
            "author": {
                "name": "guilhermeasn",
                "url": "https://github.com/guilhermeasn"
            }
        },
        {
            "content_html": "<img src=\"https://avatars.githubusercontent.com/u/55461688?u=f9ef0399a791d97fc969a32e35562ba07b3bfa7d&v=4\" width=\"64\" height=\"64\" alt=\"\"/><br/><div>A custom charting component modified from TradingView's lightweight_charts</div>",
            "url": "https://github.com/Tiqur/radium",
            "title": "Tiqur/radium: A custom charting component modified from TradingView's lightweight_charts",
            "date_modified": "2022-11-03T13:40:13.000Z",
            "date_published": "2022-11-03T13:38:33.000Z",
            "author": {
                "name": "Tiqur",
                "url": "https://github.com/Tiqur"
            }
        },
        {
            "content_html": "<img src=\"https://avatars.githubusercontent.com/u/7860859?u=46e8b0ca1c63271feccb0a7baf58cef0b0c0a488&v=4\" width=\"64\" height=\"64\" alt=\"\"/><br/><div>A lightweighted internationalization module for Deno that is simple to use.</div>",
            "url": "https://github.com/roonie007/t",
            "title": "roonie007/t: A lightweighted internationalization module for Deno that is simple to use.",
            "date_modified": "2021-11-18T03:43:15.000Z",
            "date_published": "2021-11-18T02:04:57.000Z",
            "author": {
                "name": "roonie007",
                "url": "https://github.com/roonie007"
            }
        },
        {
            "content_html": "<img src=\"https://avatars.githubusercontent.com/u/3877125?u=2d25765b57a891cf90218fdd7604b027dd3b7a87&v=4\" width=\"64\" height=\"64\" alt=\"\"/><br/><div>Lightweight JSX-based UI framework with boilerplate-free state managament.</div>",
            "url": "https://github.com/oamaok/kaiku",
            "title": "oamaok/kaiku: Lightweight JSX-based UI framework with boilerplate-free state managament.",
            "date_modified": "2022-11-02T12:18:54.000Z",
            "date_published": "2021-07-11T22:26:36.000Z",
            "author": {
                "name": "oamaok",
                "url": "https://github.com/oamaok"
            }
        },
        {
            "content_html": "<img src=\"https://avatars.githubusercontent.com/u/75171656?v=4\" width=\"64\" height=\"64\" alt=\"\"/><br/><div>Jspreadsheet is a lightweight vanilla javascript plugin to create amazing web-based interactive tables and spreadsheets compatible with other spreadsheet software.</div>",
            "url": "https://github.com/jspreadsheet/ce",
            "title": "jspreadsheet/ce: Jspreadsheet is a lightweight vanilla javascript plugin to create amazing web-based interactive tables and spreadsheets compatible with other spreadsheet software.",
            "date_modified": "2022-11-03T21:57:18.000Z",
            "date_published": "2017-02-20T11:48:15.000Z",
            "author": {
                "name": "jspreadsheet",
                "url": "https://github.com/jspreadsheet"
            }
        },
        {
            "content_html": "<img src=\"https://avatars.githubusercontent.com/u/11795356?v=4\" width=\"64\" height=\"64\" alt=\"\"/><br/><div>A simple lightweight markup language with HTML output. Implementations in JavaScript and Python 3 available.</div>",
            "url": "https://github.com/Xitog/hamill",
            "title": "Xitog/hamill: A simple lightweight markup language with HTML output. Implementations in JavaScript and Python 3 available.",
            "date_modified": "2022-09-30T16:30:08.000Z",
            "date_published": "2021-03-06T18:02:53.000Z",
            "author": {
                "name": "Xitog",
                "url": "https://github.com/Xitog"
            }
        },
        {
            "content_html": "<img src=\"https://avatars.githubusercontent.com/u/42539315?u=ca5ae67e0fce9aa74b9f8fed7bcf165d33ad226e&v=4\" width=\"64\" height=\"64\" alt=\"\"/><br/><div>Banka is a lightweight application for banking transactions. It was built with Node.js, Express, Vanilla JavaScript, HTML and CSS</div>",
            "url": "https://github.com/chialuka/Banka-App",
            "title": "chialuka/Banka-App: Banka is a lightweight application for banking transactions. It was built with Node.js, Express, Vanilla JavaScript, HTML and CSS",
            "date_modified": "2022-01-23T08:01:45.000Z",
            "date_published": "2019-03-26T19:24:17.000Z",
            "author": {
                "name": "chialuka",
                "url": "https://github.com/chialuka"
            }
        },
        {
            "content_html": "<img src=\"https://avatars.githubusercontent.com/u/18489846?v=4\" width=\"64\" height=\"64\" alt=\"\"/><br/><div>Lit is a simple library for building fast, lightweight web components.</div>",
            "url": "https://github.com/lit/lit",
            "title": "lit/lit: Lit is a simple library for building fast, lightweight web components.",
            "date_modified": "2022-11-03T22:28:50.000Z",
            "date_published": "2017-06-29T16:27:16.000Z",
            "author": {
                "name": "lit",
                "url": "https://github.com/lit"
            }
        },
        {
            "content_html": "<img src=\"https://avatars.githubusercontent.com/u/656699?u=5110d9622b331d2c9bfb8d3e10c3983699cd8925&v=4\" width=\"64\" height=\"64\" alt=\"\"/><br/><div>An ultra lightweight implementation of the `setImmediate` API.</div>",
            "url": "https://github.com/ryancdotorg/setImmediateLite",
            "title": "ryancdotorg/setImmediateLite: An ultra lightweight implementation of the `setImmediate` API.",
            "date_modified": "2022-11-03T21:03:07.000Z",
            "date_published": "2022-11-03T21:02:55.000Z",
            "author": {
                "name": "ryancdotorg",
                "url": "https://github.com/ryancdotorg"
            }
        },
        {
            "content_html": "<img src=\"https://avatars.githubusercontent.com/u/74061612?u=e9a2a32b7fa4409b708933db9738c20b81710e12&v=4\" width=\"64\" height=\"64\" alt=\"\"/><br/><div>lightweight buggy platformer engine for physics and rendering</div>",
            "url": "https://github.com/Genius6942/platformer-engine",
            "title": "Genius6942/platformer-engine: lightweight buggy platformer engine for physics and rendering",
            "date_modified": "2022-10-30T00:51:52.000Z",
            "date_published": "2022-10-27T18:58:28.000Z",
            "author": {
                "name": "Genius6942",
                "url": "https://github.com/Genius6942"
            }
        },
        {
            "content_html": "<img src=\"https://avatars.githubusercontent.com/u/93453289?v=4\" width=\"64\" height=\"64\" alt=\"\"/><br/><div>A lightweight alternative to PteroJS</div>",
            "url": "https://github.com/PteroPackages/PteroJSLite",
            "title": "PteroPackages/PteroJSLite: A lightweight alternative to PteroJS",
            "date_modified": "2022-10-27T21:08:44.000Z",
            "date_published": "2022-02-08T00:05:11.000Z",
            "author": {
                "name": "PteroPackages",
                "url": "https://github.com/PteroPackages"
            }
        },
        {
            "content_html": "<img src=\"https://avatars.githubusercontent.com/u/21335119?u=c70ffc495b48d4d5be098d8f2ca0ff325f052417&v=4\" width=\"64\" height=\"64\" alt=\"\"/><br/><div>A fully type-safe and lightweight internationalization library for all your TypeScript and JavaScript projects.</div>",
            "url": "https://github.com/ivanhofer/typesafe-i18n",
            "title": "ivanhofer/typesafe-i18n: A fully type-safe and lightweight internationalization library for all your TypeScript and JavaScript projects.",
            "date_modified": "2022-11-04T00:10:58.000Z",
            "date_published": "2020-12-28T10:50:32.000Z",
            "author": {
                "name": "ivanhofer",
                "url": "https://github.com/ivanhofer"
            }
        },
        {
            "content_html": "<img src=\"https://avatars.githubusercontent.com/u/29347852?u=5d25d4e727f1912ce5d9ed194a44c2d83147f672&v=4\" width=\"64\" height=\"64\" alt=\"\"/><br/><div>Fast, simple and lightweight Redis client library for Deno.</div>",
            "url": "https://github.com/iuioiua/r2d2",
            "title": "iuioiua/r2d2: Fast, simple and lightweight Redis client library for Deno.",
            "date_modified": "2022-11-03T20:10:17.000Z",
            "date_published": "2022-06-30T22:29:22.000Z",
            "author": {
                "name": "iuioiua",
                "url": "https://github.com/iuioiua"
            }
        },
        {
            "content_html": "<img src=\"https://avatars.githubusercontent.com/u/106556793?u=a18448516ae32fd3afa5d2dd8db67effeb41a798&v=4\" width=\"64\" height=\"64\" alt=\"\"/><br/><div>Lightweight, configurable and simple bar chart library in JavaScript</div>",
            "url": "https://github.com/br-andrebelem/bar-chart-js",
            "title": "br-andrebelem/bar-chart-js: Lightweight, configurable and simple bar chart library in JavaScript",
            "date_modified": "2022-11-03T16:35:50.000Z",
            "date_published": "2022-11-03T15:29:42.000Z",
            "author": {
                "name": "br-andrebelem",
                "url": "https://github.com/br-andrebelem"
            }
        },
        {
            "content_html": "<img src=\"https://avatars.githubusercontent.com/u/34131810?v=4\" width=\"64\" height=\"64\" alt=\"\"/><br/><div>A lightweight, highly customizable storefront.</div>",
            "url": "https://github.com/cityssm/mini-shop",
            "title": "cityssm/mini-shop: A lightweight, highly customizable storefront.",
            "date_modified": "2022-11-03T17:16:20.000Z",
            "date_published": "2020-09-15T14:15:23.000Z",
            "author": {
                "name": "cityssm",
                "url": "https://github.com/cityssm"
            }
        },
        {
            "content_html": "<img src=\"https://avatars.githubusercontent.com/u/22273943?u=e1ad92bebb1f868d3ca81d256c2bc0d6c84c83a1&v=4\" width=\"64\" height=\"64\" alt=\"\"/><br/><div>Lightweight and Elegant Multiuser and Multiprocess Object Store with Conflict Tracking [Object Database]</div>",
            "url": "https://github.com/fantasyui-com/cuddlemuffin",
            "title": "fantasyui-com/cuddlemuffin: Lightweight and Elegant Multiuser and Multiprocess Object Store with Conflict Tracking [Object Database]",
            "date_modified": "2022-04-08T21:16:12.000Z",
            "date_published": "2018-06-18T21:33:43.000Z",
            "author": {
                "name": "fantasyui-com",
                "url": "https://github.com/fantasyui-com"
            }
        },
        {
            "content_html": "<img src=\"https://avatars.githubusercontent.com/u/9806346?u=a88059ddf7842b4162c48997ca72e12102830cff&v=4\" width=\"64\" height=\"64\" alt=\"\"/><br/><div>A small and lightweight framework for making web components and prototypes.</div>",
            "url": "https://github.com/haydncomley/smol",
            "title": "haydncomley/smol: A small and lightweight framework for making web components and prototypes.",
            "date_modified": "2022-11-03T19:04:36.000Z",
            "date_published": "2022-11-03T19:00:51.000Z",
            "author": {
                "name": "haydncomley",
                "url": "https://github.com/haydncomley"
            }
        },
        {
            "content_html": "<img src=\"https://avatars.githubusercontent.com/u/60198665?v=4\" width=\"64\" height=\"64\" alt=\"\"/><br/><div>A lightweight, open source, and self-hosted alternative to linktree in a Docker container!</div>",
            "url": "https://github.com/techno-tim/littlelink-server",
            "title": "techno-tim/littlelink-server: A lightweight, open source, and self-hosted alternative to linktree in a Docker container!",
            "date_modified": "2022-11-01T08:05:46.000Z",
            "date_published": "2021-08-10T02:53:44.000Z",
            "author": {
                "name": "techno-tim",
                "url": "https://github.com/techno-tim"
            }
        },
        {
            "content_html": "<img src=\"https://avatars.githubusercontent.com/u/3895928?u=27b46ab5d423e524258d4163cda58ab71060db76&v=4\" width=\"64\" height=\"64\" alt=\"\"/><br/><div>touch-friendly lightweight chalkboard</div>",
            "url": "https://github.com/r0d1on/chalkboard",
            "title": "r0d1on/chalkboard: touch-friendly lightweight chalkboard",
            "date_modified": "2022-07-04T21:14:18.000Z",
            "date_published": "2020-06-07T22:20:52.000Z",
            "author": {
                "name": "r0d1on",
                "url": "https://github.com/r0d1on"
            }
        }
    ]
}