{
    "version": "https://jsonfeed.org/version/1",
    "title": "LightWeight JavaScript repositories",
    "home_page_url": "https://azu.github.io/github-search-rss/lightweight-javascript-repo.json",
    "feed_url": "https://azu.github.io/github-search-rss/lightweight-javascript-repo.json",
    "description": "LightWeight JavaScript repositories on GitHub",
    "items": [
        {
            "content_html": "<img src=\"https://avatars.githubusercontent.com/u/83924639?u=1ce90f917abb3bb82c84351e738ea51a5e81cb84&v=4\" width=\"64\" height=\"64\" alt=\"\"/><br/><div>A lightweight Node.js library for AES and DES encryption, offering flexible encoding options, support for various cipher modes, and seamless integration with streams.</div>",
            "url": "https://github.com/kiki-kanri/node-ciphers",
            "title": "kiki-kanri/node-ciphers: A lightweight Node.js library for AES and DES encryption, offering flexible encoding options, support for various cipher modes, and seamless integration with streams.",
            "date_modified": "2024-08-26T11:01:13.000Z",
            "date_published": "2023-11-14T04:07:11.000Z",
            "author": {
                "name": "kiki-kanri",
                "url": "https://github.com/kiki-kanri"
            }
        },
        {
            "content_html": "<img src=\"https://avatars.githubusercontent.com/u/47165568?v=4\" width=\"64\" height=\"64\" alt=\"\"/><br/><div>Simple, lightweight, and easy to use SauceNAO API wrapper for Node.JS.</div>",
            "url": "https://github.com/ClarityCafe/Sagiri",
            "title": "ClarityCafe/Sagiri: Simple, lightweight, and easy to use SauceNAO API wrapper for Node.JS.",
            "date_modified": "2024-08-26T10:58:02.000Z",
            "date_published": "2017-04-24T02:42:05.000Z",
            "author": {
                "name": "ClarityCafe",
                "url": "https://github.com/ClarityCafe"
            }
        },
        {
            "content_html": "<img src=\"https://avatars.githubusercontent.com/u/108532180?v=4\" width=\"64\" height=\"64\" alt=\"\"/><br/><div>Lightweight bi-directional conversion between DUIS and JSON</div>",
            "url": "https://github.com/SmartDCCInnovation/duis-parser",
            "title": "SmartDCCInnovation/duis-parser: Lightweight bi-directional conversion between DUIS and JSON",
            "date_modified": "2024-08-26T10:57:15.000Z",
            "date_published": "2022-07-20T14:55:42.000Z",
            "author": {
                "name": "SmartDCCInnovation",
                "url": "https://github.com/SmartDCCInnovation"
            }
        },
        {
            "content_html": "<img src=\"https://avatars.githubusercontent.com/u/10920102?u=52baecb350e819a7cb6b46a6e207cc2cfea1af7e&v=4\" width=\"64\" height=\"64\" alt=\"\"/><br/><div>Lightweight (&lt; 1.6kB gzipped) and performant natural sorting of arrays and collections by differentiating between unicode characters, numbers, dates, etc.</div>",
            "url": "https://github.com/yobacca/natural-orderby",
            "title": "yobacca/natural-orderby: Lightweight (< 1.6kB gzipped) and performant natural sorting of arrays and collections by differentiating between unicode characters, numbers, dates, etc.",
            "date_modified": "2024-08-26T10:53:29.000Z",
            "date_published": "2018-06-26T23:04:26.000Z",
            "author": {
                "name": "yobacca",
                "url": "https://github.com/yobacca"
            }
        },
        {
            "content_html": "<img src=\"https://avatars.githubusercontent.com/u/14338007?u=f3f98b96dc619176260a91079dec7025e135343b&v=4\" width=\"64\" height=\"64\" alt=\"\"/><br/><div>Envelop is a lightweight library allowing developers to easily develop, share, collaborate and extend their GraphQL execution layer. Envelop is the missing GraphQL plugin system. </div>",
            "url": "https://github.com/n1ru4l/envelop",
            "title": "n1ru4l/envelop: Envelop is a lightweight library allowing developers to easily develop, share, collaborate and extend their GraphQL execution layer. Envelop is the missing GraphQL plugin system. ",
            "date_modified": "2024-08-26T10:47:47.000Z",
            "date_published": "2021-02-17T09:42:09.000Z",
            "author": {
                "name": "n1ru4l",
                "url": "https://github.com/n1ru4l"
            }
        },
        {
            "content_html": "<img src=\"https://avatars.githubusercontent.com/u/11529148?u=94446866c576d620cbd33e62834c480091fedcf0&v=4\" width=\"64\" height=\"64\" alt=\"\"/><br/><div>A lightweight carousel library with fluid motion and great swipe precision.</div>",
            "url": "https://github.com/davidjerleke/embla-carousel",
            "title": "davidjerleke/embla-carousel: A lightweight carousel library with fluid motion and great swipe precision.",
            "date_modified": "2024-08-26T10:44:13.000Z",
            "date_published": "2019-03-18T18:34:50.000Z",
            "author": {
                "name": "davidjerleke",
                "url": "https://github.com/davidjerleke"
            }
        },
        {
            "content_html": "<img src=\"https://avatars.githubusercontent.com/u/4573549?u=3f9564942bc5b8e0bc8097d64aca584eb927578f&v=4\" width=\"64\" height=\"64\" alt=\"\"/><br/><div>🍰 Lightweight but versatile SVG pie/donut charts for React. &lt; 2kB gzipped.</div>",
            "url": "https://github.com/toomuchdesign/react-minimal-pie-chart",
            "title": "toomuchdesign/react-minimal-pie-chart: 🍰 Lightweight but versatile SVG pie/donut charts for React. < 2kB gzipped.",
            "date_modified": "2024-08-26T10:42:46.000Z",
            "date_published": "2017-03-13T11:35:57.000Z",
            "author": {
                "name": "toomuchdesign",
                "url": "https://github.com/toomuchdesign"
            }
        },
        {
            "content_html": "<img src=\"https://avatars.githubusercontent.com/u/8744936?u=1115cf471d0dff72c78bf266dbbfe1884eb77d3d&v=4\" width=\"64\" height=\"64\" alt=\"\"/><br/><div>An ease to use auto-proxy browser extension</div>",
            "url": "https://github.com/jc3213/easy_proxy",
            "title": "jc3213/easy_proxy: An ease to use auto-proxy browser extension",
            "date_modified": "2024-08-26T10:42:22.000Z",
            "date_published": "2024-02-02T05:05:04.000Z",
            "author": {
                "name": "jc3213",
                "url": "https://github.com/jc3213"
            }
        },
        {
            "content_html": "<img src=\"https://avatars.githubusercontent.com/u/1889710?u=34d8dbbbdbb05f6748dbf1a33e826fe46212e7b2&v=4\" width=\"64\" height=\"64\" alt=\"\"/><br/><div>A very lightweight and flexible accessible modal dialog script.</div>",
            "url": "https://github.com/KittyGiraudel/a11y-dialog",
            "title": "KittyGiraudel/a11y-dialog: A very lightweight and flexible accessible modal dialog script.",
            "date_modified": "2024-08-26T10:42:07.000Z",
            "date_published": "2016-02-11T11:01:11.000Z",
            "author": {
                "name": "KittyGiraudel",
                "url": "https://github.com/KittyGiraudel"
            }
        },
        {
            "content_html": "<img src=\"https://avatars.githubusercontent.com/u/62518751?v=4\" width=\"64\" height=\"64\" alt=\"\"/><br/><div>Lightweight Dashboard to connect with Woocommerce</div>",
            "url": "https://github.com/FunkyCss/konektorx",
            "title": "FunkyCss/konektorx: Lightweight Dashboard to connect with Woocommerce",
            "date_modified": "2024-08-26T10:41:02.000Z",
            "date_published": "2024-08-23T09:57:57.000Z",
            "author": {
                "name": "FunkyCss",
                "url": "https://github.com/FunkyCss"
            }
        },
        {
            "content_html": "<img src=\"https://avatars.githubusercontent.com/u/89023470?u=de6d0a08e761f693fb8d2e4e222a1ec0c7746cba&v=4\" width=\"64\" height=\"64\" alt=\"\"/><br/><div>A simple and lightweight toast library for React</div>",
            "url": "https://github.com/thakurdotdev/toastam",
            "title": "thakurdotdev/toastam: A simple and lightweight toast library for React",
            "date_modified": "2024-08-26T10:38:43.000Z",
            "date_published": "2024-08-24T16:01:55.000Z",
            "author": {
                "name": "thakurdotdev",
                "url": "https://github.com/thakurdotdev"
            }
        },
        {
            "content_html": "<img src=\"https://avatars.githubusercontent.com/u/32372790?u=9dac470703c4e1e4893474943b530dbb21449366&v=4\" width=\"64\" height=\"64\" alt=\"\"/><br/><div>Lightweight TypeScript decorators to use with WebComponents.</div>",
            "url": "https://github.com/H1ghBre4k3r/decorator-components",
            "title": "H1ghBre4k3r/decorator-components: Lightweight TypeScript decorators to use with WebComponents.",
            "date_modified": "2024-08-26T10:38:14.000Z",
            "date_published": "2022-09-05T15:45:01.000Z",
            "author": {
                "name": "H1ghBre4k3r",
                "url": "https://github.com/H1ghBre4k3r"
            }
        },
        {
            "content_html": "<img src=\"https://avatars.githubusercontent.com/u/85643862?v=4\" width=\"64\" height=\"64\" alt=\"\"/><br/><div>ArmCord is a custom client designed to enhance your Discord experience while keeping everything lightweight.</div>",
            "url": "https://github.com/ArmCord/ArmCord",
            "title": "ArmCord/ArmCord: ArmCord is a custom client designed to enhance your Discord experience while keeping everything lightweight.",
            "date_modified": "2024-08-26T10:09:30.000Z",
            "date_published": "2020-11-16T13:33:38.000Z",
            "author": {
                "name": "ArmCord",
                "url": "https://github.com/ArmCord"
            }
        },
        {
            "content_html": "<img src=\"https://avatars.githubusercontent.com/u/3299148?v=4\" width=\"64\" height=\"64\" alt=\"\"/><br/><div>LLRT (Low Latency Runtime) is an experimental, lightweight JavaScript runtime designed to address the growing demand for fast and efficient Serverless applications.</div>",
            "url": "https://github.com/awslabs/llrt",
            "title": "awslabs/llrt: LLRT (Low Latency Runtime) is an experimental, lightweight JavaScript runtime designed to address the growing demand for fast and efficient Serverless applications.",
            "date_modified": "2024-08-26T09:55:53.000Z",
            "date_published": "2023-09-20T12:57:50.000Z",
            "author": {
                "name": "awslabs",
                "url": "https://github.com/awslabs"
            }
        },
        {
            "content_html": "<img src=\"https://avatars.githubusercontent.com/u/177488958?v=4\" width=\"64\" height=\"64\" alt=\"\"/><br/><div>A lightweight Vanilla JavaScript Dependency Injection implementation with lifecycles. </div>",
            "url": "https://github.com/hegelband/dizy",
            "title": "hegelband/dizy: A lightweight Vanilla JavaScript Dependency Injection implementation with lifecycles. ",
            "date_modified": "2024-08-26T09:54:09.000Z",
            "date_published": "2024-03-17T09:47:23.000Z",
            "author": {
                "name": "hegelband",
                "url": "https://github.com/hegelband"
            }
        },
        {
            "content_html": "<img src=\"https://avatars.githubusercontent.com/u/29024886?u=694212590b355f28a3b7c9d09bae3a4f832c9a16&v=4\" width=\"64\" height=\"64\" alt=\"\"/><br/><div>A lightweight, type-safe utility to effortlessly navigate and query deeply nested objects and arrays in JavaScript and TypeScript.</div>",
            "url": "https://github.com/daliborkoenig/nested-navigator",
            "title": "daliborkoenig/nested-navigator: A lightweight, type-safe utility to effortlessly navigate and query deeply nested objects and arrays in JavaScript and TypeScript.",
            "date_modified": "2024-08-26T09:45:50.000Z",
            "date_published": "2024-08-25T17:26:40.000Z",
            "author": {
                "name": "daliborkoenig",
                "url": "https://github.com/daliborkoenig"
            }
        },
        {
            "content_html": "<img src=\"https://avatars.githubusercontent.com/u/72567960?u=432751fc80e7dc7c3c1c710d34c27d41ef3cb6d5&v=4\" width=\"64\" height=\"64\" alt=\"\"/><br/><div>A lightweight library for integrating speech-to-text functionality into your React applications, using the Web Speech API under the hood.</div>",
            "url": "https://github.com/zohaibahmad12/react-speech-to-text-toolkit",
            "title": "zohaibahmad12/react-speech-to-text-toolkit: A lightweight library for integrating speech-to-text functionality into your React applications, using the Web Speech API under the hood.",
            "date_modified": "2024-08-26T09:53:51.000Z",
            "date_published": "2024-08-25T20:10:47.000Z",
            "author": {
                "name": "zohaibahmad12",
                "url": "https://github.com/zohaibahmad12"
            }
        },
        {
            "content_html": "<img src=\"https://avatars.githubusercontent.com/u/96433696?v=4\" width=\"64\" height=\"64\" alt=\"\"/><br/><div>Lightweight Postgres packaged as WASM into a TypeScript library for the browser, Node.js, Bun and Deno from <a href=\"https://electric-sql.com\" rel=\"nofollow\">https://electric-sql.com</a></div>",
            "url": "https://github.com/electric-sql/pglite",
            "title": "electric-sql/pglite: Lightweight Postgres packaged as WASM into a TypeScript library for the browser, Node.js, Bun and Deno from https://electric-sql.com",
            "date_modified": "2024-08-26T09:45:00.000Z",
            "date_published": "2024-02-19T14:37:38.000Z",
            "author": {
                "name": "electric-sql",
                "url": "https://github.com/electric-sql"
            }
        },
        {
            "content_html": "<img src=\"https://avatars.githubusercontent.com/u/118665057?u=bd6f181b18cc737064a2e5b175f20a15e0599172&v=4\" width=\"64\" height=\"64\" alt=\"\"/><br/><div>a  lightweight alternative to postman</div>",
            "url": "https://github.com/krabhi1/postman-clone",
            "title": "krabhi1/postman-clone: a  lightweight alternative to postman",
            "date_modified": "2024-08-26T09:27:18.000Z",
            "date_published": "2024-06-17T20:01:29.000Z",
            "author": {
                "name": "krabhi1",
                "url": "https://github.com/krabhi1"
            }
        },
        {
            "content_html": "<img src=\"https://avatars.githubusercontent.com/u/26993330?v=4\" width=\"64\" height=\"64\" alt=\"\"/><br/><div>Formique is a lightweight, declarative JavaScript syntax library for generating WCAG accessibility and usability compliant forms.</div>",
            "url": "https://github.com/Gugulethu-Nyoni/formique",
            "title": "Gugulethu-Nyoni/formique: Formique is a lightweight, declarative JavaScript syntax library for generating WCAG accessibility and usability compliant forms.",
            "date_modified": "2024-08-26T09:25:54.000Z",
            "date_published": "2024-08-16T06:16:40.000Z",
            "author": {
                "name": "Gugulethu-Nyoni",
                "url": "https://github.com/Gugulethu-Nyoni"
            }
        }
    ]
}